python3HTTPSAuthServer/__init__.py
python3HTTPSAuthServer/__main__.py
python3HTTPSAuthServer-0.1.1.dist-info/LICENSE
python3HTTPSAuthServer-0.1.1.dist-info/METADATA
python3HTTPSAuthServer-0.1.1.dist-info/WHEEL
python3HTTPSAuthServer-0.1.1.dist-info/top_level.txt
python3HTTPSAuthServer-0.1.1.dist-info/RECORD
