Metadata-Version: 2.1
Name: python3HTTPSAuthServer
Version: 0.1.1
Summary: Python3-based http.server supporting Basic AUTH and HTTPS; it's SimpleHTTPServer with python3 facial hair! 
Home-page: https://github.com/SYANiDE-/python3HTTPSAuthServer
Author: Chase Hatch
Author-email: chase.hatch.business@gmail.com
License: UNKNOWN
Platform: UNKNOWN
Classifier: Programming Language :: Python :: 3
Classifier: License :: OSI Approved :: MIT License
Classifier: Operating System :: OS Independent
